src/ESCRITURA/i2c_controller.v
module i2c_controller(
    input wire clk,
    input wire rst,
    input wire [6:0] addr,
    input wire [7:0] data_in,
    input wire enable,
    input wire rw,
    output reg [7:0] data_out,
    inout wire i2c_sda,
    inout wire i2c_scl
);

    localparam IDLE = 0;
    localparam START = 1;
    localparam ADDRESS = 2;
    localparam ACK = 3;
    localparam DATA = 4;
    localparam WAIT_ACK_DATA = 5;
    localparam STOP = 6;

    reg [2:0] state;
    reg [7:0] shift_reg;
    reg [3:0] bit_counter;

    reg scl_out, sda_out, sda_oe;
    reg scl_enable;

    assign i2c_sda = sda_oe ? sda_out : 1'b1; // SDA en alto por defecto en vez de 'z'
    assign i2c_scl = scl_enable ? scl_out : 1'b1;

    // Generación de reloj para i2c_scl
    always @(posedge clk or posedge rst) begin
        if (rst) begin
            scl_out <= 1;
            scl_enable <= 0;
        end else begin
            if (state != IDLE) scl_enable <= 1; // Activa SCL solo si no está en IDLE
            else scl_enable <= 0;
            scl_out <= ~scl_out; // Alterna el reloj
        end
    end

    // FSM para control del bus I2C
    always @(posedge clk or posedge rst) begin
        if (rst) begin
            state <= IDLE;
            sda_out <= 1; // SDA en alto por defecto
            sda_oe <= 1;  // Mantener SDA en alto inicialmente
            bit_counter <= 0;
        end else begin
            case (state)
                IDLE: begin
                    scl_out <= 1; // Mantén SCL en alto por defecto
                    sda_out <= 1; // SDA permanece en alto
                    sda_oe <= 1;  // SDA en alto, no en alta impedancia
                    if (enable) begin
                        state <= START; // Solo inicia transmisión si enable está activo
                    end
                end
                START: begin
                    sda_out <= 0; // Generar condición START
                    sda_oe <= 1; // Habilitar SDA como salida
                    if (scl_out) begin
                        state <= ADDRESS; // Ir al siguiente estado
                        shift_reg <= {addr, rw}; // Cargar dirección + bit R/W
                        bit_counter <= 7;
                    end
                end
                ADDRESS: begin
                    if (!scl_out) begin
                        sda_out <= shift_reg[bit_counter]; // Envía bits de dirección
                        sda_oe <= 1; // Habilitar SDA
                        if (bit_counter == 0) state <= ACK; // Termina dirección
                        else bit_counter <= bit_counter - 1;
                    end
                end
                ACK: begin
                    sda_oe <= 0; // Liberar SDA para leer ACK
                    if (!i2c_sda) begin // ACK recibido
                        shift_reg <= data_in; // Cargar datos para escribir
                        bit_counter <= 7;
                        state <= DATA;
                    end else begin
                        state <= STOP; // NACK recibido
                    end
                end
                DATA: begin
                    if (!scl_out) begin
                        sda_out <= shift_reg[bit_counter]; // Escribir datos
                        sda_oe <= 1; // Controlar SDA
                        if (bit_counter == 0) state <= WAIT_ACK_DATA;
                        else bit_counter <= bit_counter - 1;
                    end
                end
                WAIT_ACK_DATA: begin
                    sda_oe <= 0; // Liberar SDA para leer ACK
                    if (!i2c_sda) begin // ACK recibido
                        state <= STOP;
                    end else begin
                        state <= STOP; // NACK recibido
                    end
                end
                STOP: begin
                    scl_out <= 1; // Asegura que SCL termine en alto
                    sda_out <= 1; // Generar condición STOP (SDA pasa a alto)
                    sda_oe <= 1; // Mantener SDA en alto
                    if (!enable) begin
                        state <= IDLE; // Si enable está desactivado, vuelve a IDLE
                    end
                end
            endcase
        end
    end
endmodule

src/ESCRITURA/i2c_registers.v
module i2c_registers(
    input wire clk,
    input wire rst,
    input wire mem_valid,
    input wire [31:0] mem_addr,
    input wire [31:0] mem_wdata,
    input wire [3:0] mem_wstrb,
    output reg [31:0] mem_rdata,
    output reg mem_ready,

    // Conexiones a los registros para el controlador I2C
    output reg [31:0] i2c_bitrate,
    output reg [7:0] i2c_data_out,
    input wire [7:0] i2c_data_in,
    output reg [7:0] i2c_ctrl
);

    localparam ADDR_I2C_BITRATE = 32'h1C;
    localparam ADDR_I2C_DATA_OUT = 32'h1D;
    localparam ADDR_I2C_DATA_IN = 32'h1E;
    localparam ADDR_I2C_CTRL = 32'h1F;

    always @(posedge clk or posedge rst) begin
        if (rst) begin
            i2c_bitrate <= 32'd0;
            i2c_data_out <= 8'd0;
            i2c_ctrl <= 8'd0;
            mem_ready <= 1'b0;
            mem_rdata <= 32'd0;
        end else begin
            mem_ready <= 1'b0;

            if (mem_valid) begin
                mem_ready <= 1'b1;

                if (|mem_wstrb) begin
                    case (mem_addr)
                        ADDR_I2C_BITRATE: begin
                            if (mem_wstrb[3]) i2c_bitrate[31:24] <= mem_wdata[31:24];
                            if (mem_wstrb[2]) i2c_bitrate[23:16] <= mem_wdata[23:16];
                            if (mem_wstrb[1]) i2c_bitrate[15:8] <= mem_wdata[15:8];
                            if (mem_wstrb[0]) i2c_bitrate[7:0] <= mem_wdata[7:0];
                        end
                        ADDR_I2C_DATA_OUT: if (mem_wstrb[0]) i2c_data_out <= mem_wdata[7:0];
                        ADDR_I2C_CTRL: if (mem_wstrb[0]) i2c_ctrl <= mem_wdata[7:0];
                    endcase
                end else begin
                    case (mem_addr)
                        ADDR_I2C_BITRATE: mem_rdata <= i2c_bitrate;
                        ADDR_I2C_DATA_OUT: mem_rdata <= {24'd0, i2c_data_out};
                        ADDR_I2C_DATA_IN: mem_rdata <= {24'd0, i2c_data_in};
                        ADDR_I2C_CTRL: mem_rdata <= {24'd0, i2c_ctrl};
                        default: mem_rdata <= 32'd0;
                    endcase
                end
            end
        end
    end
endmodule

src/ESCRITURA/top.v
module i2c_top(
    input wire clk,
    input wire rst,
    input wire mem_valid,
    input wire [31:0] mem_addr,
    input wire [31:0] mem_wdata,
    input wire [3:0] mem_wstrb,
    output wire [31:0] mem_rdata,
    output wire mem_ready,
    inout wire i2c_sda,
    inout wire i2c_scl
);

    wire [31:0] i2c_bitrate;
    wire [7:0] i2c_data_out;
    wire [7:0] i2c_data_in;
    wire [7:0] i2c_ctrl_wire;  
    reg [7:0] i2c_ctrl_reg;    

    wire [6:0] addr = i2c_data_out[7:1];
    wire rw = i2c_data_out[0];
    wire enable = i2c_ctrl_wire[6];

    i2c_registers u_i2c_registers (
        .clk(clk),
        .rst(rst),
        .mem_valid(mem_valid),
        .mem_addr(mem_addr),
        .mem_wdata(mem_wdata),
        .mem_wstrb(mem_wstrb),
        .mem_rdata(mem_rdata),
        .mem_ready(mem_ready),
        .i2c_bitrate(i2c_bitrate),
        .i2c_data_out(i2c_data_out),
        .i2c_data_in(i2c_data_in),
        .i2c_ctrl(i2c_ctrl_wire)
    );

    always @(posedge clk or posedge rst) begin
        if (rst) begin
            i2c_ctrl_reg <= 8'd0;
        end else begin
            i2c_ctrl_reg <= i2c_ctrl_wire;
        end
    end

    i2c_controller u_i2c_controller (
        .clk(clk),
        .rst(rst),
        .addr(addr),
        .data_in(i2c_data_out),
        .enable(enable),
        .rw(rw),
        .data_out(i2c_data_in),
        .i2c_sda(i2c_sda),
        .i2c_scl(i2c_scl)
    );
endmodule

src/ESCRITURA/top_tb.v
module i2c_top_tb;

    reg clk;
    reg rst;
    reg mem_valid;
    reg [31:0] mem_addr;
    reg [31:0] mem_wdata;
    reg [3:0] mem_wstrb;
    wire [31:0] mem_rdata;
    wire mem_ready;
    wire i2c_sda;
    wire i2c_scl;

    i2c_top uut (
        .clk(clk),
        .rst(rst),
        .mem_valid(mem_valid),
        .mem_addr(mem_addr),
        .mem_wdata(mem_wdata),
        .mem_wstrb(mem_wstrb),
        .mem_rdata(mem_rdata),
        .mem_ready(mem_ready),
        .i2c_sda(i2c_sda),
        .i2c_scl(i2c_scl)
    );

    initial begin
        clk = 0;
        forever #10 clk = ~clk; // Ajustar el tiempo del reloj para una simulación más lenta
    end

    initial begin
        $dumpfile("i2c_top_tb.vcd");
        $dumpvars(0, i2c_top_tb);

        // Inicialización del sistema
        rst = 1; mem_valid = 0; mem_addr = 0; mem_wdata = 0; mem_wstrb = 0;
        #40 rst = 0;

        // Configuración inicial del bitrate
        write_register(32'h1C, 32'd500000); // Configurar bitrate
        #20;

        // Enviar dirección del periférico
        write_register(32'h1D, 8'hAA); // Dirección + R/W
        #20;

        // Enviar comando para iniciar transmisión (START + dirección)
        write_register(32'h1F, 8'b01010000);
        #200; // Tiempo extendido para observar claramente las señales

        // Cambiar valor del registro para enviar el dato
        write_register(32'h1D, 8'h55); // Dato a enviar
        #20;

        // Enviar dato al periférico
        write_register(32'h1F, 8'b01001000);
        #200; // Tiempo extendido para observar el envío del dato

        // Generar condición de parada (STOP)
        write_register(32'h1F, 8'b00100000);
        #200; // Tiempo extendido para observar la condición STOP

        $finish; // Finaliza la simulación
    end

    task write_register(input [31:0] addr, input [31:0] data);
        begin
            mem_valid = 1; mem_addr = addr; mem_wdata = data; mem_wstrb = 4'b1111;
            #20 mem_valid = 0; // Ajustar tiempo para mantener el registro activado
        end
    endtask
endmodule

src/ESCRITURA/i2c_top_tb.vcd
$date
	Mon Nov 18 04:38:42 2024
$end
$version
	Icarus Verilog
$end
$timescale
	1ps
$end
$scope module i2c_top_tb $end
$var wire 1 ! mem_ready $end
$var wire 32 " mem_rdata [31:0] $end
$var wire 1 # i2c_sda $end
$var wire 1 $ i2c_scl $end
$var reg 1 % clk $end
$var reg 32 & mem_addr [31:0] $end
$var reg 1 ' mem_valid $end
$var reg 32 ( mem_wdata [31:0] $end
$var reg 4 ) mem_wstrb [3:0] $end
$var reg 1 * rst $end
$scope module uut $end
$var wire 1 % clk $end
$var wire 32 + mem_addr [31:0] $end
$var wire 1 ' mem_valid $end
$var wire 32 , mem_wdata [31:0] $end
$var wire 4 - mem_wstrb [3:0] $end
$var wire 1 * rst $end
$var wire 1 . rw $end
$var wire 1 ! mem_ready $end
$var wire 32 / mem_rdata [31:0] $end
$var wire 1 # i2c_sda $end
$var wire 1 $ i2c_scl $end
$var wire 8 0 i2c_data_out [7:0] $end
$var wire 8 1 i2c_data_in [7:0] $end
$var wire 8 2 i2c_ctrl_wire [7:0] $end
$var wire 32 3 i2c_bitrate [31:0] $end
$var wire 1 4 enable $end
$var wire 7 5 addr [6:0] $end
$var reg 8 6 i2c_ctrl_reg [7:0] $end
$scope module u_i2c_controller $end
$var wire 7 7 addr [6:0] $end
$var wire 1 % clk $end
$var wire 1 4 enable $end
$var wire 1 * rst $end
$var wire 1 . rw $end
$var wire 1 # i2c_sda $end
$var wire 1 $ i2c_scl $end
$var wire 8 8 data_in [7:0] $end
$var parameter 32 9 ACK $end
$var parameter 32 : ADDRESS $end
$var parameter 32 ; DATA $end
$var parameter 32 < IDLE $end
$var parameter 32 = START $end
$var parameter 32 > STOP $end
$var parameter 32 ? WAIT_ACK_DATA $end
$var reg 4 @ bit_counter [3:0] $end
$var reg 8 A data_out [7:0] $end
$var reg 1 B scl_enable $end
$var reg 1 C scl_out $end
$var reg 1 D sda_oe $end
$var reg 1 E sda_out $end
$var reg 8 F shift_reg [7:0] $end
$var reg 3 G state [2:0] $end
$upscope $end
$scope module u_i2c_registers $end
$var wire 1 % clk $end
$var wire 8 H i2c_data_in [7:0] $end
$var wire 32 I mem_addr [31:0] $end
$var wire 1 ' mem_valid $end
$var wire 32 J mem_wdata [31:0] $end
$var wire 4 K mem_wstrb [3:0] $end
$var wire 1 * rst $end
$var parameter 32 L ADDR_I2C_BITRATE $end
$var parameter 32 M ADDR_I2C_CTRL $end
$var parameter 32 N ADDR_I2C_DATA_IN $end
$var parameter 32 O ADDR_I2C_DATA_OUT $end
$var reg 32 P i2c_bitrate [31:0] $end
$var reg 8 Q i2c_ctrl [7:0] $end
$var reg 8 R i2c_data_out [7:0] $end
$var reg 32 S mem_rdata [31:0] $end
$var reg 1 ! mem_ready $end
$upscope $end
$upscope $end
$scope task write_register $end
$var reg 32 T addr [31:0] $end
$var reg 32 U data [31:0] $end
$upscope $end
$upscope $end
$enddefinitions $end
$comment Show the parameter values. $end
$dumpall
b11101 O
b11110 N
b11111 M
b11100 L
b101 ?
b110 >
b1 =
b0 <
b100 ;
b10 :
b11 9
$end
#0
$dumpvars
bx U
bx T
b0 S
b0 R
b0 Q
b0 P
b0 K
b0 J
b0 I
bx H
b0 G
bx F
1E
1D
1C
0B
bx A
b0 @
b0 8
b0 7
b0 6
b0 5
04
b0 3
b0 2
bx 1
b0 0
b0 /
0.
b0 -
b0 ,
b0 +
1*
b0 )
b0 (
0'
b0 &
0%
1$
1#
b0 "
0!
$end
#10000
1%
#20000
0%
#30000
1%
#40000
0%
b1111 )
b1111 -
b1111 K
b1111010000100100000 (
b1111010000100100000 ,
b1111010000100100000 J
b11100 &
b11100 +
b11100 I
1'
b1111010000100100000 U
b11100 T
0*
#50000
1C
b1111010000100100000 3
b1111010000100100000 P
1!
1%
#60000
0%
0'
#70000
0!
0C
1%
#80000
0%
b10101010 (
b10101010 ,
b10101010 J
b11101 &
b11101 +
b11101 I
1'
b10101010 U
b11101 T
#90000
b1010101 5
b1010101 7
1C
b10101010 0
b10101010 8
b10101010 R
1!
1%
#100000
0%
0'
#110000
0!
0C
1%
#120000
0%
b1010000 (
b1010000 ,
b1010000 J
b11111 &
b11111 +
b11111 I
1'
b1010000 U
b11111 T
#130000
14
1C
b1010000 2
b1010000 Q
1!
1%
#140000
0%
0'
#150000
0!
0C
b1 G
b1010000 6
1%
#160000
0%
#170000
0#
0E
1C
1B
1%
#180000
0%
#190000
0$
0C
b111 @
b10101010 F
b10 G
1%
#200000
0%
#210000
1#
1$
b110 @
1E
1C
1%
#220000
0%
#230000
0$
0C
1%
#240000
0%
#250000
0#
1$
b101 @
0E
1C
1%
#260000
0%
#270000
0$
0C
1%
#280000
0%
#290000
1#
1$
b100 @
1E
1C
1%
#300000
0%
#310000
0$
0C
1%
#320000
0%
#330000
0#
1$
b11 @
0E
1C
1%
#340000
0%
b1010101 (
b1010101 ,
b1010101 J
b11101 &
b11101 +
b11101 I
1'
b1010101 U
b11101 T
#350000
1.
b101010 5
b101010 7
0$
b1010101 0
b1010101 8
b1010101 R
1!
0C
1%
#360000
0%
0'
#370000
1#
1$
b10 @
1E
1C
0!
1%
#380000
0%
b1001000 (
b1001000 ,
b1001000 J
b11111 &
b11111 +
b11111 I
1'
b1001000 U
b11111 T
#390000
0$
b1001000 2
b1001000 Q
1!
0C
1%
#400000
0%
0'
#410000
0#
1$
b1001000 6
b1 @
0E
1C
0!
1%
#420000
0%
#430000
0$
0C
1%
#440000
0%
#450000
1#
1$
b0 @
1E
1C
1%
#460000
0%
#470000
0$
0C
1%
#480000
0%
#490000
0#
1$
b11 G
0E
1C
1%
#500000
0%
#510000
0$
1#
0C
b100 G
b111 @
b1010101 F
0D
1%
#520000
0%
#530000
0#
1$
b110 @
1D
1C
1%
#540000
0%
#550000
0$
0C
1%
#560000
0%
#570000
1#
1$
b101 @
1E
1C
1%
#580000
0%
#590000
0$
0C
1%
#600000
0%
b100000 (
b100000 ,
b100000 J
1'
b100000 U
#610000
0#
1$
04
b100 @
0E
1C
b100000 2
b100000 Q
1!
1%
#620000
0%
0'
#630000
0$
0!
0C
b100000 6
1%
#640000
0%
#650000
1#
1$
b11 @
1E
1C
1%
#660000
0%
#670000
0$
0C
1%
#680000
0%
#690000
0#
1$
b10 @
0E
1C
1%
#700000
0%
#710000
0$
0C
1%
#720000
0%
#730000
1#
1$
b1 @
1E
1C
1%
#740000
0%
#750000
0$
0C
1%
#760000
0%
#770000
0#
1$
b0 @
0E
1C
1%
#780000
0%
#790000
0$
0C
1%
#800000
0%
#810000
1#
1$
b101 G
1E
1C
1%
