src/LECTURA/i2c_controller.v
module i2c_controller(
    input wire clk,
    input wire rst,
    input wire [6:0] addr,
    input wire [7:0] data_in,
    input wire enable,
    input wire rw, // 0: Escritura, 1: Lectura
    output reg [7:0] data_out, // Dato recibido
    inout wire i2c_sda,
    inout wire i2c_scl
);

    localparam IDLE = 0;
    localparam START = 1;
    localparam ADDRESS = 2;
    localparam ACK = 3;
    localparam DATA = 4;
    localparam READ_DATA = 5; // Nuevo estado para leer datos
    localparam WAIT_ACK_DATA = 6;
    localparam STOP = 7;

    reg [2:0] state;
    reg [7:0] shift_reg;
    reg [3:0] bit_counter;

    reg scl_out, sda_out, sda_oe;
    reg scl_enable;

    assign i2c_sda = sda_oe ? sda_out : 1'bz; // SDA en alta impedancia si no se controla
    assign i2c_scl = scl_enable ? scl_out : 1'b1;

    // Generación de reloj para i2c_scl
    always @(posedge clk or posedge rst) begin
        if (rst) begin
            scl_out <= 1;
            scl_enable <= 0;
        end else begin
            if (state != IDLE) scl_enable <= 1; // Activa SCL solo si no está en IDLE
            else scl_enable <= 0;
            scl_out <= ~scl_out; // Alterna el reloj
        end
    end

    // FSM para control del bus I2C
    always @(posedge clk or posedge rst) begin
        if (rst) begin
            state <= IDLE;
            sda_out <= 1; // SDA en alto por defecto
            sda_oe <= 1;  // Mantener SDA en alto inicialmente
            bit_counter <= 0;
            data_out <= 8'd0; // Limpiar salida de datos
        end else begin
            case (state)
                IDLE: begin
                    scl_out <= 1; // Mantén SCL en alto por defecto
                    sda_out <= 1; // SDA permanece en alto
                    sda_oe <= 1;  // SDA en alto, no en alta impedancia
                    if (enable) begin
                        state <= START; // Solo inicia transmisión si enable está activo
                    end
                end
                START: begin
                    sda_out <= 0; // Generar condición START
                    sda_oe <= 1; // Habilitar SDA como salida
                    if (scl_out) begin
                        state <= ADDRESS; // Ir al siguiente estado
                        shift_reg <= {addr, rw}; // Cargar dirección + bit R/W
                        bit_counter <= 7;
                    end
                end
                ADDRESS: begin
                    if (!scl_out) begin
                        sda_out <= shift_reg[bit_counter]; // Envía bits de dirección
                        sda_oe <= 1; // Habilitar SDA
                        if (bit_counter == 0) state <= ACK; // Termina dirección
                        else bit_counter <= bit_counter - 1;
                    end
                end
                ACK: begin
                    sda_oe <= 0; // Liberar SDA para leer ACK
                    if (!i2c_sda) begin // ACK recibido
                        bit_counter <= 7;
                        if (rw == 0) begin
                            // Escritura
                            shift_reg <= data_in; // Cargar datos para escribir
                            state <= DATA;
                        end else begin
                            // Lectura
                            state <= READ_DATA; // Pasar a leer datos
                        end
                    end else begin
                        state <= STOP; // NACK recibido
                    end
                end
                DATA: begin
                    if (!scl_out) begin
                        sda_out <= shift_reg[bit_counter]; // Escribir datos
                        sda_oe <= 1; // Controlar SDA
                        if (bit_counter == 0) state <= WAIT_ACK_DATA;
                        else bit_counter <= bit_counter - 1;
                    end
                end
                READ_DATA: begin
                    if (scl_out) begin // Captura datos en el flanco de subida de SCL
                        shift_reg[bit_counter] <= i2c_sda; // Leer bit desde SDA
                        if (bit_counter == 0) begin
                            data_out <= shift_reg; // Transferir los datos recibidos al registro paralelo
                            state <= WAIT_ACK_DATA; // Pasar al estado de ACK/NACK
                        end else begin
                            bit_counter <= bit_counter - 1; // Avanzar al siguiente bit
                        end
                    end
                end
                WAIT_ACK_DATA: begin
                    sda_out <= 0; // Enviar ACK (poner SDA en 0)
                    sda_oe <= 1;  // Controlar SDA
                    if (!scl_out) begin // Flanco de bajada de SCL
                        state <= STOP; // Pasar al estado STOP
                    end
                end
                STOP: begin
                    scl_out <= 1; // Asegura que SCL termine en alto
                    sda_out <= 1; // Generar condición STOP (SDA pasa a alto)
                    sda_oe <= 1; // Mantener SDA en alto
                    if (!enable) begin
                        state <= IDLE; // Si enable está desactivado, vuelve a IDLE
                    end
                end
            endcase
        end
    end
endmodule

src/ESCRITURA/i2c_registers.v
module i2c_registers(
    input wire clk,
    input wire rst,
    input wire mem_valid,
    input wire [31:0] mem_addr,
    input wire [31:0] mem_wdata,
    input wire [3:0] mem_wstrb,
    output reg [31:0] mem_rdata,
    output reg mem_ready,

    // Conexiones a los registros para el controlador I2C
    output reg [31:0] i2c_bitrate,
    output reg [7:0] i2c_data_out,
    input wire [7:0] i2c_data_in,
    output reg [7:0] i2c_ctrl
);

    localparam ADDR_I2C_BITRATE = 32'h1C;
    localparam ADDR_I2C_DATA_OUT = 32'h1D;
    localparam ADDR_I2C_DATA_IN = 32'h1E;
    localparam ADDR_I2C_CTRL = 32'h1F;

    always @(posedge clk or posedge rst) begin
        if (rst) begin
            i2c_bitrate <= 32'd0;
            i2c_data_out <= 8'd0;
            i2c_ctrl <= 8'd0;
            mem_ready <= 1'b0;
            mem_rdata <= 32'd0;
        end else begin
            mem_ready <= 1'b0;

            if (mem_valid) begin
                mem_ready <= 1'b1;

                if (|mem_wstrb) begin
                    case (mem_addr)
                        ADDR_I2C_BITRATE: begin
                            if (mem_wstrb[3]) i2c_bitrate[31:24] <= mem_wdata[31:24];
                            if (mem_wstrb[2]) i2c_bitrate[23:16] <= mem_wdata[23:16];
                            if (mem_wstrb[1]) i2c_bitrate[15:8] <= mem_wdata[15:8];
                            if (mem_wstrb[0]) i2c_bitrate[7:0] <= mem_wdata[7:0];
                        end
                        ADDR_I2C_DATA_OUT: if (mem_wstrb[0]) i2c_data_out <= mem_wdata[7:0];
                        ADDR_I2C_CTRL: if (mem_wstrb[0]) i2c_ctrl <= mem_wdata[7:0];
                    endcase
                end else begin
                    case (mem_addr)
                        ADDR_I2C_BITRATE: mem_rdata <= i2c_bitrate;
                        ADDR_I2C_DATA_OUT: mem_rdata <= {24'd0, i2c_data_out};
                        ADDR_I2C_DATA_IN: mem_rdata <= {24'd0, i2c_data_in};
                        ADDR_I2C_CTRL: mem_rdata <= {24'd0, i2c_ctrl};
                        default: mem_rdata <= 32'd0;
                    endcase
                end
            end
        end
    end
endmodule

src/ESCRITURA/top.v
module i2c_top(
    input wire clk,
    input wire rst,
    input wire mem_valid,
    input wire [31:0] mem_addr,
    input wire [31:0] mem_wdata,
    input wire [3:0] mem_wstrb,
    output wire [31:0] mem_rdata,
    output wire mem_ready,
    inout wire i2c_sda,
    inout wire i2c_scl
);

    wire [31:0] i2c_bitrate;
    wire [7:0] i2c_data_out;
    wire [7:0] i2c_data_in;
    wire [7:0] i2c_ctrl_wire;  
    reg [7:0] i2c_ctrl_reg;    

    wire [6:0] addr = i2c_data_out[7:1];
    wire rw = i2c_data_out[0];
    wire enable = i2c_ctrl_wire[6];

    i2c_registers u_i2c_registers (
        .clk(clk),
        .rst(rst),
        .mem_valid(mem_valid),
        .mem_addr(mem_addr),
        .mem_wdata(mem_wdata),
        .mem_wstrb(mem_wstrb),
        .mem_rdata(mem_rdata),
        .mem_ready(mem_ready),
        .i2c_bitrate(i2c_bitrate),
        .i2c_data_out(i2c_data_out),
        .i2c_data_in(i2c_data_in),
        .i2c_ctrl(i2c_ctrl_wire)
    );

    always @(posedge clk or posedge rst) begin
        if (rst) begin
            i2c_ctrl_reg <= 8'd0;
        end else begin
            i2c_ctrl_reg <= i2c_ctrl_wire;
        end
    end

    i2c_controller u_i2c_controller (
        .clk(clk),
        .rst(rst),
        .addr(addr),
        .data_in(i2c_data_out),
        .enable(enable),
        .rw(rw),
        .data_out(i2c_data_in),
        .i2c_sda(i2c_sda),
        .i2c_scl(i2c_scl)
    );
endmodule

src/LECTURA/top_tb.v
`timescale 1ns / 1ps

module i2c_top_tb;

    // Señales del banco de pruebas
    reg clk;
    reg rst;
    reg mem_valid;
    reg [31:0] mem_addr;
    reg [31:0] mem_wdata;
    reg [3:0] mem_wstrb;
    wire [31:0] mem_rdata;
    wire mem_ready;
    tri i2c_sda; // Línea de datos bidireccional
    wire i2c_scl; // Línea de reloj

    // Instancia del módulo `i2c_top`
    i2c_top uut (
        .clk(clk),
        .rst(rst),
        .mem_valid(mem_valid),
        .mem_addr(mem_addr),
        .mem_wdata(mem_wdata),
        .mem_wstrb(mem_wstrb),
        .mem_rdata(mem_rdata),
        .mem_ready(mem_ready),
        .i2c_sda(i2c_sda),
        .i2c_scl(i2c_scl)
    );

    // Generación de reloj
    initial begin
        clk = 0;
        forever #10 clk = ~clk; // Período del reloj: 20 ns
    end

    // Secuencia de prueba
    initial begin
        // Configuración para volcado de simulación
        $dumpfile("i2c_top_tb.vcd"); // Archivo de salida para GTKWave
        $dumpvars(0, i2c_top_tb);    // Volcar todas las variables del módulo testbench

        // Inicialización
        rst = 1;
        mem_valid = 0;
        mem_addr = 0;
        mem_wdata = 0;
        mem_wstrb = 0;
        #50 rst = 0; // Desactiva el reset después de 50 ns

        // Configuración inicial del bitrate
        write_register(32'h1C, 32'd500000); // Configurar bitrate
        #20;

        // Lectura desde el periférico
        write_register(32'h1D, 8'b10101001); // Dirección del esclavo + RW (lectura)
        #20;
        write_register(32'h1F, 8'b01010000); // Generar START y enviar dirección
        #200;

        // Leer el dato recibido desde el esclavo
        read_register(32'h1E); // Leer dato desde el registro i2c_data_in
        #200;

        $finish; // Finaliza la simulación
    end

    // Tareas para escritura y lectura en los registros
    task write_register(input [31:0] addr, input [31:0] data);
        begin
            mem_valid = 1;
            mem_addr = addr;
            mem_wdata = data;
            mem_wstrb = 4'b1111;
            #20 mem_valid = 0; // Desactiva mem_valid después de un ciclo
        end
    endtask

    task read_register(input [31:0] addr);
        begin
            mem_valid = 1;
            mem_addr = addr;
            mem_wstrb = 4'b0000; // No se realiza escritura
            #20 mem_valid = 0; // Desactiva mem_valid después de un ciclo
            $display("Dato leído en la dirección %h: %h", addr, mem_rdata);
        end
    endtask

endmodule

src/LECTURA/i2c_top_tb.vcd
$date
	Thu Nov 21 16:59:26 2024
$end
$version
	Icarus Verilog
$end
$timescale
	1ps
$end
$scope module i2c_top_tb $end
$var wire 1 ! mem_ready $end
$var wire 32 " mem_rdata [31:0] $end
$var wire 1 # i2c_sda $end
$var wire 1 $ i2c_scl $end
$var reg 1 % clk $end
$var reg 32 & mem_addr [31:0] $end
$var reg 1 ' mem_valid $end
$var reg 32 ( mem_wdata [31:0] $end
$var reg 4 ) mem_wstrb [3:0] $end
$var reg 1 * rst $end
$scope module uut $end
$var wire 1 % clk $end
$var wire 32 + mem_addr [31:0] $end
$var wire 1 ' mem_valid $end
$var wire 32 , mem_wdata [31:0] $end
$var wire 4 - mem_wstrb [3:0] $end
$var wire 1 * rst $end
$var wire 1 . rw $end
$var wire 1 ! mem_ready $end
$var wire 32 / mem_rdata [31:0] $end
$var wire 1 # i2c_sda $end
$var wire 1 $ i2c_scl $end
$var wire 8 0 i2c_data_out [7:0] $end
$var wire 8 1 i2c_data_in [7:0] $end
$var wire 8 2 i2c_ctrl_wire [7:0] $end
$var wire 32 3 i2c_bitrate [31:0] $end
$var wire 1 4 enable $end
$var wire 7 5 addr [6:0] $end
$var reg 8 6 i2c_ctrl_reg [7:0] $end
$scope module u_i2c_controller $end
$var wire 7 7 addr [6:0] $end
$var wire 1 % clk $end
$var wire 1 4 enable $end
$var wire 1 * rst $end
$var wire 1 . rw $end
$var wire 1 # i2c_sda $end
$var wire 1 $ i2c_scl $end
$var wire 8 8 data_in [7:0] $end
$var parameter 32 9 ACK $end
$var parameter 32 : ADDRESS $end
$var parameter 32 ; DATA $end
$var parameter 32 < IDLE $end
$var parameter 32 = READ_DATA $end
$var parameter 32 > START $end
$var parameter 32 ? STOP $end
$var parameter 32 @ WAIT_ACK_DATA $end
$var reg 4 A bit_counter [3:0] $end
$var reg 8 B data_out [7:0] $end
$var reg 1 C scl_enable $end
$var reg 1 D scl_out $end
$var reg 1 E sda_oe $end
$var reg 1 F sda_out $end
$var reg 8 G shift_reg [7:0] $end
$var reg 3 H state [2:0] $end
$upscope $end
$scope module u_i2c_registers $end
$var wire 1 % clk $end
$var wire 8 I i2c_data_in [7:0] $end
$var wire 32 J mem_addr [31:0] $end
$var wire 1 ' mem_valid $end
$var wire 32 K mem_wdata [31:0] $end
$var wire 4 L mem_wstrb [3:0] $end
$var wire 1 * rst $end
$var parameter 32 M ADDR_I2C_BITRATE $end
$var parameter 32 N ADDR_I2C_CTRL $end
$var parameter 32 O ADDR_I2C_DATA_IN $end
$var parameter 32 P ADDR_I2C_DATA_OUT $end
$var reg 32 Q i2c_bitrate [31:0] $end
$var reg 8 R i2c_ctrl [7:0] $end
$var reg 8 S i2c_data_out [7:0] $end
$var reg 32 T mem_rdata [31:0] $end
$var reg 1 ! mem_ready $end
$upscope $end
$upscope $end
$scope task read_register $end
$var reg 32 U addr [31:0] $end
$upscope $end
$scope task write_register $end
$var reg 32 V addr [31:0] $end
$var reg 32 W data [31:0] $end
$upscope $end
$upscope $end
$enddefinitions $end
$comment Show the parameter values. $end
$dumpall
b11101 P
b11110 O
b11111 N
b11100 M
b110 @
b111 ?
b1 >
b101 =
b0 <
b100 ;
b10 :
b11 9
$end
#0
$dumpvars
bx W
bx V
bx U
b0 T
b0 S
b0 R
b0 Q
b0 L
b0 K
b0 J
b0 I
b0 H
bx G
1F
1E
1D
0C
b0 B
b0 A
b0 8
b0 7
b0 6
b0 5
04
b0 3
b0 2
b0 1
b0 0
b0 /
0.
b0 -
b0 ,
b0 +
1*
b0 )
b0 (
0'
b0 &
0%
1$
1#
b0 "
0!
$end
#10000
1%
#20000
0%
#30000
1%
#40000
0%
#50000
1D
b1111010000100100000 3
b1111010000100100000 Q
1!
1%
b1111 )
b1111 -
b1111 L
b1111010000100100000 (
b1111010000100100000 ,
b1111010000100100000 K
b11100 &
b11100 +
b11100 J
1'
b1111010000100100000 W
b11100 V
0*
#60000
0%
#70000
0!
0D
1%
0'
#80000
0%
#90000
1.
b1010100 5
b1010100 7
1D
b10101001 0
b10101001 8
b10101001 S
1!
1%
b10101001 (
b10101001 ,
b10101001 K
b11101 &
b11101 +
b11101 J
1'
b10101001 W
b11101 V
#100000
0%
#110000
0!
0D
1%
0'
#120000
0%
#130000
14
1D
b1010000 2
b1010000 R
1!
1%
b1010000 (
b1010000 ,
b1010000 K
b11111 &
b11111 +
b11111 J
1'
b1010000 W
b11111 V
#140000
0%
#150000
0!
0D
b1 H
b1010000 6
1%
0'
#160000
0%
#170000
0#
0F
1D
1C
1%
#180000
0%
#190000
0$
0D
b111 A
b10101001 G
b10 H
1%
#200000
0%
#210000
1#
1$
b110 A
1F
1D
1%
#220000
0%
#230000
0$
0D
1%
#240000
0%
#250000
0#
1$
b101 A
0F
1D
1%
#260000
0%
#270000
0$
0D
1%
#280000
0%
#290000
1#
1$
b100 A
1F
1D
1%
#300000
0%
#310000
0$
0D
1%
#320000
0%
#330000
0#
1$
b11 A
0F
1D
1%
#340000
0%
#350000
0$
1!
0D
1%
b0 )
b0 -
b0 L
b11110 &
b11110 +
b11110 J
1'
b11110 U
#360000
0%
#370000
1#
1$
b10 A
1F
1D
0!
1%
0'
#380000
0%
#390000
0$
0D
1%
#400000
0%
#410000
0#
1$
b1 A
0F
1D
1%
#420000
0%
#430000
0$
0D
1%
#440000
0%
#450000
1$
b0 A
1D
1%
#460000
0%
#470000
0$
0D
1%
#480000
0%
#490000
1#
1$
b11 H
1F
1D
1%
#500000
0%
#510000
0$
z#
0D
b111 H
0E
1%
#520000
0%
#530000
1#
1$
1E
1D
1%
#540000
0%
#550000
0$
0D
1%
#560000
0%
#570000
1$
1D
1%
